pymc_sphinx_theme/__init__.py
pymc_sphinx_theme/layout.html
pymc_sphinx_theme/search.html
pymc_sphinx_theme/theme.conf
pymc_sphinx_theme/components/donate.html
pymc_sphinx_theme/components/edit-this-page.html
pymc_sphinx_theme/components/navbar-version.html
pymc_sphinx_theme/components/pymc_icon_links.html
pymc_sphinx_theme/components/search-button.html
pymc_sphinx_theme/components/search-field.html
pymc_sphinx_theme/static/css/style.css
pymc_sphinx_theme/static/js/readthedocs.js
pymc_sphinx_theme-0.16.0.dist-info/entry_points.txt
pymc_sphinx_theme-0.16.0.dist-info/licenses/LICENSE
pymc_sphinx_theme-0.16.0.dist-info/WHEEL
pymc_sphinx_theme-0.16.0.dist-info/METADATA
pymc_sphinx_theme-0.16.0.dist-info/RECORD
